TypescriptHandbookZhongwenban/README.md
TypescriptHandbookZhongwenban/__init__.py
TypescriptHandbookZhongwenban/__main__.py
TypescriptHandbookZhongwenban/file.epub
TypescriptHandbookZhongwenban/index.html
TypescriptHandbookZhongwenban/css/__init__.py
TypescriptHandbookZhongwenban/css/annotations.css
TypescriptHandbookZhongwenban/css/main.css
TypescriptHandbookZhongwenban/css/normalize.css
TypescriptHandbookZhongwenban/css/popup.css
TypescriptHandbookZhongwenban/font/__init__.py
TypescriptHandbookZhongwenban/font/fontello.eot
TypescriptHandbookZhongwenban/font/fontello.svg
TypescriptHandbookZhongwenban/font/fontello.ttf
TypescriptHandbookZhongwenban/font/fontello.woff
TypescriptHandbookZhongwenban/img/__init__.py
TypescriptHandbookZhongwenban/img/annotator-glyph-sprite.png
TypescriptHandbookZhongwenban/img/annotator-icon-sprite.png
TypescriptHandbookZhongwenban/img/apple-touch-icon.png
TypescriptHandbookZhongwenban/img/cancelfullscreen.png
TypescriptHandbookZhongwenban/img/close.png
TypescriptHandbookZhongwenban/img/fullscreen.png
TypescriptHandbookZhongwenban/img/loader.gif
TypescriptHandbookZhongwenban/img/menu-icon.png
TypescriptHandbookZhongwenban/img/save.png
TypescriptHandbookZhongwenban/img/saved.png
TypescriptHandbookZhongwenban/img/settings-s.png
TypescriptHandbookZhongwenban/img/settings.png
TypescriptHandbookZhongwenban/img/star.png
TypescriptHandbookZhongwenban/js/__init__.py
TypescriptHandbookZhongwenban/js/epub.js
TypescriptHandbookZhongwenban/js/epub.min.js
TypescriptHandbookZhongwenban/js/epub.min.map
TypescriptHandbookZhongwenban/js/hooks.min.js
TypescriptHandbookZhongwenban/js/hooks.min.map
TypescriptHandbookZhongwenban/js/reader.js
TypescriptHandbookZhongwenban/js/reader.js.map
TypescriptHandbookZhongwenban/js/reader.min.js
TypescriptHandbookZhongwenban/js/reader.min.map
TypescriptHandbookZhongwenban/js/hooks/__init__.py
TypescriptHandbookZhongwenban/js/hooks/extensions/__init__.py
TypescriptHandbookZhongwenban/js/hooks/extensions/highlight.js
typescript_handbook_zhongwenban-2024.3.2.0.dist-info/METADATA
typescript_handbook_zhongwenban-2024.3.2.0.dist-info/WHEEL
typescript_handbook_zhongwenban-2024.3.2.0.dist-info/entry_points.txt
typescript_handbook_zhongwenban-2024.3.2.0.dist-info/top_level.txt
typescript_handbook_zhongwenban-2024.3.2.0.dist-info/RECORD
